example_package1/Beta_Splitting_Model.py
example_package1/CN.py
example_package1/Gen_Ref_Fa.py
example_package1/__init__.py
example_package1/__main__.py
example_package1/calculate_lorenz.py
example_package1/estimate_beta_dist.py
example_package1/example.py
example_package1/flip_counter.py
example_package1/gen_newick.py
example_package1/gen_newick_chr.py
example_package1/gen_readcount.py
example_package1/gen_tree.py
example_package1/gen_tree_overlappingCNA.py
example_package1/main.par.overlapping.py
example_package1/main.par.py
example_package1/metropolis_hasting.py
example_package1/read_tree.py
example_package1_xianfanmallory-0.1.5.dist-info/LICENSE
example_package1_xianfanmallory-0.1.5.dist-info/METADATA
example_package1_xianfanmallory-0.1.5.dist-info/WHEEL
example_package1_xianfanmallory-0.1.5.dist-info/top_level.txt
example_package1_xianfanmallory-0.1.5.dist-info/RECORD
